koverse/__init__.py
koverse/client.py
koverse/spark.py
koverse/transformTest.py
koverse/thriftgen/__init__.py
koverse/thriftgen/constants.py
koverse/thriftgen/ttypes.py
koverse/thriftgen/addon/AddOnService.py
koverse/thriftgen/addon/__init__.py
koverse/thriftgen/addon/constants.py
koverse/thriftgen/addon/ttypes.py
koverse/thriftgen/admin/AdminService.py
koverse/thriftgen/admin/__init__.py
koverse/thriftgen/admin/constants.py
koverse/thriftgen/admin/ttypes.py
koverse/thriftgen/appauth/AppAuthService.py
koverse/thriftgen/appauth/__init__.py
koverse/thriftgen/appauth/constants.py
koverse/thriftgen/appauth/ttypes.py
koverse/thriftgen/audit/AuditService.py
koverse/thriftgen/audit/__init__.py
koverse/thriftgen/audit/constants.py
koverse/thriftgen/audit/ttypes.py
koverse/thriftgen/collection/CollectionService.py
koverse/thriftgen/collection/__init__.py
koverse/thriftgen/collection/constants.py
koverse/thriftgen/collection/ttypes.py
koverse/thriftgen/dataflow/DataFlowService.py
koverse/thriftgen/dataflow/__init__.py
koverse/thriftgen/dataflow/constants.py
koverse/thriftgen/dataflow/ttypes.py
koverse/thriftgen/internal/InternalService.py
koverse/thriftgen/internal/__init__.py
koverse/thriftgen/internal/constants.py
koverse/thriftgen/internal/ttypes.py
koverse/thriftgen/notification/NotificationService.py
koverse/thriftgen/notification/__init__.py
koverse/thriftgen/notification/constants.py
koverse/thriftgen/notification/ttypes.py
koverse/thriftgen/queryservice/QueryService.py
koverse/thriftgen/queryservice/__init__.py
koverse/thriftgen/queryservice/constants.py
koverse/thriftgen/queryservice/ttypes.py
koverse/thriftgen/resource/ResourceService.py
koverse/thriftgen/resource/__init__.py
koverse/thriftgen/resource/constants.py
koverse/thriftgen/resource/ttypes.py
koverse/thriftgen/security/__init__.py
koverse/thriftgen/security/constants.py
koverse/thriftgen/security/ttypes.py
koverse/thriftgen/top/__init__.py
koverse/thriftgen/top/constants.py
koverse/thriftgen/top/ttypes.py
koverse-3.7.0.0.dist-info/METADATA
koverse-3.7.0.0.dist-info/WHEEL
koverse-3.7.0.0.dist-info/top_level.txt
koverse-3.7.0.0.dist-info/RECORD
