Metadata-Version: 2.1
Name: koverse
Version: 3.7.0.0
Summary: Koverse Python Client
Home-page: http://www.koverse.com/support/developers/
Author: Koverse Inc.
Author-email: support@koverse.com
License: Apache Software License
Keywords: koverse python
Platform: UNKNOWN
Classifier: Development Status :: 3 - Alpha
Classifier: Intended Audience :: Developers
Classifier: Topic :: Software Development :: Build Tools
Classifier: License :: OSI Approved :: Apache Software License
Classifier: Programming Language :: Python :: 2
Classifier: Programming Language :: Python :: 2.6
Classifier: Programming Language :: Python :: 2.7
Classifier: Programming Language :: Python :: 3
Requires-Dist: thrift
